pydantic2_schemaorg/AMRadioChannel.py
pydantic2_schemaorg/APIReference.py
pydantic2_schemaorg/Abdomen.py
pydantic2_schemaorg/AboutPage.py
pydantic2_schemaorg/AcceptAction.py
pydantic2_schemaorg/Accommodation.py
pydantic2_schemaorg/AccountingService.py
pydantic2_schemaorg/AchieveAction.py
pydantic2_schemaorg/Action.py
pydantic2_schemaorg/ActionAccessSpecification.py
pydantic2_schemaorg/ActionStatusType.py
pydantic2_schemaorg/ActivateAction.py
pydantic2_schemaorg/ActivationFee.py
pydantic2_schemaorg/ActiveActionStatus.py
pydantic2_schemaorg/ActiveNotRecruiting.py
pydantic2_schemaorg/AddAction.py
pydantic2_schemaorg/AdministrativeArea.py
pydantic2_schemaorg/AdultEntertainment.py
pydantic2_schemaorg/AdultOrientedEnumeration.py
pydantic2_schemaorg/AdvertiserContentArticle.py
pydantic2_schemaorg/AerobicActivity.py
pydantic2_schemaorg/AggregateOffer.py
pydantic2_schemaorg/AggregateRating.py
pydantic2_schemaorg/AgreeAction.py
pydantic2_schemaorg/Airline.py
pydantic2_schemaorg/Airport.py
pydantic2_schemaorg/AlbumRelease.py
pydantic2_schemaorg/AlcoholConsideration.py
pydantic2_schemaorg/AlgorithmicMediaDigitalSource.py
pydantic2_schemaorg/AlgorithmicallyEnhancedDigitalSource.py
pydantic2_schemaorg/AlignmentObject.py
pydantic2_schemaorg/AllWheelDriveConfiguration.py
pydantic2_schemaorg/AllergiesHealthAspect.py
pydantic2_schemaorg/AllocateAction.py
pydantic2_schemaorg/AmpStory.py
pydantic2_schemaorg/AmusementPark.py
pydantic2_schemaorg/AnaerobicActivity.py
pydantic2_schemaorg/AnalysisNewsArticle.py
pydantic2_schemaorg/AnatomicalStructure.py
pydantic2_schemaorg/AnatomicalSystem.py
pydantic2_schemaorg/AndroidPlatform.py
pydantic2_schemaorg/Anesthesia.py
pydantic2_schemaorg/AnimalShelter.py
pydantic2_schemaorg/Answer.py
pydantic2_schemaorg/Apartment.py
pydantic2_schemaorg/ApartmentComplex.py
pydantic2_schemaorg/Appearance.py
pydantic2_schemaorg/AppendAction.py
pydantic2_schemaorg/ApplyAction.py
pydantic2_schemaorg/ApprovedIndication.py
pydantic2_schemaorg/Aquarium.py
pydantic2_schemaorg-0.3.0.dist-info/LICENSE
pydantic2_schemaorg-0.3.0.dist-info/METADATA
pydantic2_schemaorg-0.3.0.dist-info/WHEEL
pydantic2_schemaorg-0.3.0.dist-info/RECORD
