Metadata-Version: 2.3
Name: pydantic2-schemaorg
Version: 0.3.0
Summary: Pydantic classes for Schema.org
Home-page: https://github.com/blurry-dev/pydantic2-schemaorg
License: MIT
Keywords: schema.org,pydantic
Author: John Franey
Requires-Python: >=3.10,<4.0
Classifier: License :: OSI Approved :: MIT License
Classifier: Programming Language :: Python :: 3
Classifier: Programming Language :: Python :: 3.10
Classifier: Programming Language :: Python :: 3.11
Classifier: Programming Language :: Python :: 3.12
Classifier: Programming Language :: Python :: 3.13
Requires-Dist: pydantic (>=2.9.2,<3.0.0)
Project-URL: Documentation, https://github.com/blurry-dev/pydantic2-schemaorg
Project-URL: Repository, https://github.com/blurry-dev/pydantic2-schemaorg
